setup.cfg
setup.py
nose_test_select/__init__.py
nose_test_select/nose_test_select.py
nose_test_select.egg-info/PKG-INFO
nose_test_select.egg-info/SOURCES.txt
nose_test_select.egg-info/dependency_links.txt
nose_test_select.egg-info/entry_points.txt
nose_test_select.egg-info/not-zip-safe
nose_test_select.egg-info/pbr.json
nose_test_select.egg-info/requires.txt
nose_test_select.egg-info/top_level.txt