Metadata-Version: 1.1
Name: nose-test-select
Version: 0.3
Summary: .gitignore style test selection for nose (file and method name globbing)
Home-page: http://github.com/EnigmaCurry/nose-test-select
Author: Ryan McGuire
Author-email: ryan@enigmacurry.com
License: MIT
Platform: UNKNOWN
Classifier: Intended Audience :: Developers
Classifier: Topic :: Software Development :: Testing
Classifier: License :: OSI Approved :: MIT License
